neobrainfuck/__init__.py
neobrainfuck/core.py
neobrainfuck-1.1.0.dist-info/LICENSE
neobrainfuck-1.1.0.dist-info/METADATA
neobrainfuck-1.1.0.dist-info/WHEEL
neobrainfuck-1.1.0.dist-info/top_level.txt
neobrainfuck-1.1.0.dist-info/RECORD
