Metadata-Version: 2.1
Name: neobrainfuck
Version: 1.1.0
Summary: Just another rethink of the BrainFuck language
Home-page: https://github.com/kusrabyzarc/NeoBrainF--k
Author: kusrabyzarc
Author-email: crazybarsuk@mail.ru
Keywords: BrainFuck interpreter extended programming language esolang development python library brainfuck-interpreter esoteric extended-brainfuck
Classifier: Development Status :: 4 - Beta
Classifier: Intended Audience :: Developers
Classifier: License :: OSI Approved :: MIT License
Classifier: Programming Language :: Python :: 3
Classifier: Programming Language :: Python :: 3.7
Classifier: Programming Language :: Python :: 3.8
Classifier: Programming Language :: Python :: 3.9
Classifier: Programming Language :: Python :: 3.10
Classifier: Programming Language :: Python :: Implementation :: CPython
Classifier: Programming Language :: Python :: Implementation :: PyPy
Classifier: Topic :: Software Development :: Interpreters
Classifier: Topic :: Software Development :: Libraries :: Python Modules
Requires-Python: >=3.10
License-File: LICENSE
